README.md
setup.py
SQLshite.egg-info/PKG-INFO
SQLshite.egg-info/SOURCES.txt
SQLshite.egg-info/dependency_links.txt
SQLshite.egg-info/requires.txt
SQLshite.egg-info/top_level.txt
sqlshite/__init__.py
sqlshite/__main__.py
sqlshite/_version.py
sqlshite/web/__init__.py
sqlshite/web/wsgi.py
sqlshite/web/www/jsonform.html
sqlshite/web/www/list_databases.html
sqlshite/web/www/list_tables.html
sqlshite/web/www/sql_editor.html
sqlshite/web/www/table_explorer.html
sqlshite/web/www/viewform.html
sqlshite/web/www/css/bootstrap.css
sqlshite/web/www/js/jquery.min.js
sqlshite/web/www/js/jsonform.js
sqlshite/web/www/js/jsv.js
sqlshite/web/www/js/shortcut.js
sqlshite/web/www/js/underscore.js