Metadata-Version: 2.1
Name: SQLshite
Version: 0.0.0.dev2
Summary: Tools for dealing with SQLite3 and jsonform
Home-page: https://github.com/clach04/SQLshite
Author: clach04
License: GNU Affero General Public License v3 or later (AGPLv3+)
Platform: any
Classifier: Development Status :: 4 - Beta
Classifier: License :: OSI Approved :: GNU Affero General Public License v3 or later (AGPLv3+)
Classifier: Operating System :: OS Independent
Classifier: Programming Language :: Python
Classifier: Programming Language :: Python :: 2
Classifier: Programming Language :: Python :: 2.7
Classifier: Programming Language :: Python :: 3
Classifier: Programming Language :: Python :: 3.8
Classifier: Programming Language :: Python :: 3.12
Classifier: Topic :: Database
Classifier: Topic :: File Formats :: JSON
Classifier: Topic :: File Formats :: JSON :: JSON Schema
Classifier: Programming Language :: SQL
